irnl_rdt_correction/__init__.py
irnl_rdt_correction/__main__.py
irnl_rdt_correction/constants.py
irnl_rdt_correction/equation_system.py
irnl_rdt_correction/input_options.py
irnl_rdt_correction/io_handling.py
irnl_rdt_correction/main.py
irnl_rdt_correction/rdt_handling.py
irnl_rdt_correction/utilities.py
irnl_rdt_correction-1.1.2.dist-info/METADATA
irnl_rdt_correction-1.1.2.dist-info/WHEEL
irnl_rdt_correction-1.1.2.dist-info/licenses/LICENSE
irnl_rdt_correction-1.1.2.dist-info/RECORD
